runtime_client/__init__.py
runtime_client/__version__.py
runtime_client/api.py
runtime_client/client.py
runtime_client-0.1.2.dist-info/METADATA
runtime_client-0.1.2.dist-info/WHEEL
runtime_client-0.1.2.dist-info/top_level.txt
runtime_client-0.1.2.dist-info/RECORD
